yaml2object/__init__.py
yaml2object/errors.py
yaml2object/node.py
yaml2object/node_meta.py
yaml2object/yaml_loader.py
yaml2object/yaml_object.py
yaml2object-1.0.13.dist-info/LICENSE
yaml2object-1.0.13.dist-info/METADATA
yaml2object-1.0.13.dist-info/WHEEL
yaml2object-1.0.13.dist-info/top_level.txt
yaml2object-1.0.13.dist-info/zip-safe
yaml2object-1.0.13.dist-info/RECORD
